autogen_ext_yepcode/__init__.py
autogen_ext_yepcode/_yepcode_executor.py
autogen_ext_yepcode/py.typed
autogen_ext_yepcode-0.1.0.dist-info/LICENSE
autogen_ext_yepcode-0.1.0.dist-info/METADATA
autogen_ext_yepcode-0.1.0.dist-info/WHEEL
autogen_ext_yepcode-0.1.0.dist-info/RECORD
